directed_inputs_class/__init__.py
directed_inputs_class/__main__.py
directed_inputs_class-1.0.0.dist-info/METADATA
directed_inputs_class-1.0.0.dist-info/WHEEL
directed_inputs_class-1.0.0.dist-info/licenses/LICENSE
directed_inputs_class-1.0.0.dist-info/RECORD
