Metadata-Version: 2.3
Name: directed-inputs-class
Version: 1.0.0
Summary: Directed inputs class consumes and processes inputs from sources beyond args and kwargs
Project-URL: Documentation, https://github.com/jbcom/directed-inputs-class#readme
Project-URL: Issues, https://github.com/jbcom/directed-inputs-class/issues
Project-URL: Source, https://github.com/jbcom/directed-inputs-class
Author-email: Jon Bogaty <jon@jonbogaty.com>
Maintainer-email: Jon Bogaty <jon@jonbogaty.com>
License-Expression: MIT
License-File: LICENSE
Keywords: python3
Classifier: Development Status :: 5 - Production/Stable
Classifier: License :: OSI Approved :: MIT License
Classifier: Programming Language :: Python :: 3.9
Classifier: Programming Language :: Python :: 3.10
Classifier: Programming Language :: Python :: 3.11
Classifier: Programming Language :: Python :: 3.12
Classifier: Typing :: Typed
Requires-Python: >=3.9
Requires-Dist: case-insensitive-dictionary>=0.2.1
Requires-Dist: deepmerge>=1.1.1
Requires-Dist: extended-data-types>=3.0.1
Requires-Dist: future>=1.0.0
Provides-Extra: docs
Requires-Dist: docutils>=0.17; extra == 'docs'
Requires-Dist: myst-parser>=3.0.1; extra == 'docs'
Requires-Dist: sphinx-autodoc2>=0.5.0; extra == 'docs'
Requires-Dist: sphinx<7.5,>=7.2; extra == 'docs'
Requires-Dist: sphinxawesome-theme>=5.2.0; extra == 'docs'
Provides-Extra: tests
Requires-Dist: coverage[toml]>=7.6.0; extra == 'tests'
Requires-Dist: pytest-cov>=5.0.0; extra == 'tests'
Requires-Dist: pytest-mock>=3.14.0; extra == 'tests'
Requires-Dist: pytest-xdist>=3.6.1; extra == 'tests'
Requires-Dist: pytest>=8.2.2; extra == 'tests'
Provides-Extra: typing
Requires-Dist: mypy>=1.0.0; extra == 'typing'
Requires-Dist: sortedcontainers-stubs>=2.4.2; extra == 'typing'
Requires-Dist: types-pyyaml>=6.0.12.20240724; extra == 'typing'
